commonroad_reach/__init__.py
commonroad_reach/__version__.py
commonroad_reach/py.typed
commonroad_reach/pycrreach.cpython-311-x86_64-linux-gnu.so
commonroad_reach/pycrreach.pyi
commonroad_reach/configurations_default/__init__.py
commonroad_reach/configurations_default/debug.yaml
commonroad_reach/configurations_default/general.yaml
commonroad_reach/configurations_default/planning.yaml
commonroad_reach/configurations_default/reachable_set.yaml
commonroad_reach/configurations_default/vehicle.yaml
commonroad_reach/data_structure/__init__.py
commonroad_reach/data_structure/collision_checker.py
commonroad_reach/data_structure/configuration.py
commonroad_reach/data_structure/configuration_builder.py
commonroad_reach/data_structure/regular_grid.py
commonroad_reach/data_structure/segment_tree.py
commonroad_reach/data_structure/reach/__init__.py
commonroad_reach/data_structure/reach/driving_corridor.py
commonroad_reach/data_structure/reach/driving_corridor_extractor.py
commonroad_reach/data_structure/reach/reach_interface.py
commonroad_reach/data_structure/reach/reach_line.py
commonroad_reach/data_structure/reach/reach_node.py
commonroad_reach/data_structure/reach/reach_polygon.py
commonroad_reach/data_structure/reach/reach_set.py
commonroad_reach/data_structure/reach/reach_set_cpp.py
commonroad_reach/data_structure/reach/reach_set_py.py
commonroad_reach/data_structure/reach/reach_set_py_graph_offline.py
commonroad_reach/data_structure/reach/reach_set_py_graph_online.py
commonroad_reach/data_structure/reach/reach_vertex.py
commonroad_reach/utility/__init__.py
commonroad_reach/utility/configuration.py
commonroad_reach/utility/coordinate_system.py
commonroad_reach/utility/general.py
commonroad_reach/utility/geometry.py
commonroad_reach/utility/logger.py
commonroad_reach/utility/reach_operation.py
commonroad_reach/utility/sweep_line.py
commonroad_reach/utility/util_py_grid_online_reach.pyx
commonroad_reach/utility/visualization.py
commonroad_reach-2025.2.0.dist-info/METADATA
commonroad_reach-2025.2.0.dist-info/WHEEL
commonroad_reach-2025.2.0.dist-info/RECORD
commonroad_reach-2025.2.0.dist-info/licenses/LICENSE.txt
