Metadata-Version: 2.1
Name: commonroad-reach
Version: 2025.2.0
Summary: A Toolbox for Computing Reachable Sets of Automated Vehicles
Keywords: autonomous vehicles,automated driving,motion planning,reachability analysis
Author-Email: Cyber-Physical Systems Group - Technical University of Munich <commonroad@lists.lrz.de>
License: Copyright (c) 2021, Cyber-Physical Systems Group, Technical University of Munich.
Classifier: Programming Language :: C++
Classifier: Programming Language :: Python :: 3.10
Classifier: Programming Language :: Python :: 3.11
Classifier: License :: OSI Approved :: BSD License
Classifier: Operating System :: POSIX :: Linux
Project-URL: Homepage, https://commonroad.in.tum.de/tools/commonroad-reach
Project-URL: Documentation, https://commonroad.in.tum.de/docs/commonroad-reach/
Project-URL: Forum, https://commonroad.in.tum.de/forum/c/commonroad-reach/19
Project-URL: Source, https://gitlab.lrz.de/tum-cps/commonroad-reach
Requires-Python: <3.12,>=3.10
Requires-Dist: commonroad-io~=2024.1
Requires-Dist: commonroad-route-planner~=2025.1.0
Requires-Dist: commonroad-drivability-checker~=2025.3.0
Requires-Dist: commonroad-clcs~=2025.2.0
Requires-Dist: cython~=3.0
Requires-Dist: imageio~=2.9
Requires-Dist: matplotlib~=3.3
Requires-Dist: networkx~=3.0
Requires-Dist: numpy<3.0,>=1.19
Requires-Dist: omegaconf~=2.1
Requires-Dist: opencv-python~=4.5
Requires-Dist: scipy~=1.4
Requires-Dist: seaborn~=0.10
Requires-Dist: shapely~=2.0
Provides-Extra: test
Requires-Dist: pytest>=3.8.0; extra == "test"
Provides-Extra: docs
Requires-Dist: Sphinx>=4.5.0; extra == "docs"
Requires-Dist: sphinx-autodoc-typehints>=1.18.1; extra == "docs"
Requires-Dist: sphinx-rtd-theme>=2.0.0; extra == "docs"
Requires-Dist: m2r2>=0.3.0; extra == "docs"
Requires-Dist: docutils<0.21,>=0.18.1; extra == "docs"
Provides-Extra: build
Requires-Dist: scikit-build-core~=0.11.0; extra == "build"
Requires-Dist: nanobind~=2.2.0; extra == "build"
Requires-Dist: pathspec>=0.12.1; extra == "build"
Requires-Dist: pyproject-metadata>=0.7.1; extra == "build"
Requires-Dist: typing_extensions~=4.12.2; extra == "build"
Requires-Dist: cmake<4.0,>=3.24; extra == "build"
